libname/__init__.py
libname/example.py
example_addone_v01-0.0.1.dist-info/METADATA
example_addone_v01-0.0.1.dist-info/WHEEL
example_addone_v01-0.0.1.dist-info/top_level.txt
example_addone_v01-0.0.1.dist-info/RECORD
