Metadata-Version: 2.1
Name: example-addone-v01
Version: 0.0.1
Summary: add one simple
Home-page: UNKNOWN
Author: matin (Florian Dedov)
Author-email: matingottasickmind@gmail.com
License: UNKNOWN
Platform: UNKNOWN
Classifier: Development Status :: 1 - Planning
Classifier: Intended Audience :: Developers
Classifier: Programming Language :: Python :: 3
Classifier: Operating System :: Unix
